[
  {
    "id": "Aceite",
    "name": "Aceite"
  },
  {
    "id": "Acondicionador",
    "name": "Acondicionador"
  },
  {
    "id": "Caja de Ampollas",
    "name": "Caja de Ampollas"
  },
  {
    "id": "Champú",
    "name": "Champú"
  },
  {
    "id": "Crema",
    "name": "Crema"
  },
  {
    "id": "Fluido",
    "name": "Fluido"
  },
  {
    "id": "Gotas",
    "name": "Gotas"
  },
  {
    "id": "Goteros",
    "name": "Goteros"
  },
  {
    "id": "Kit",
    "name": "Kit"
  },
  {
    "id": "Leaven",
    "name": "Leaven"
  },
  {
    "id": "Mascarilla",
    "name": "Mascarilla"
  },
  {
    "id": "Oleo",
    "name": "Oleo"
  },
  {
    "id": "Serum",
    "name": "Serum"
  },
  {
    "id": "Tonico",
    "name": "Tonico"
  },
  {
    "id": "Tratamiento",
    "name": "Tratamiento"
  }
]